django_statsd/__about__.py
django_statsd/__init__.py
django_statsd/celery.py
django_statsd/database.py
django_statsd/json.py
django_statsd/middleware.py
django_statsd/redis.py
django_statsd/settings.py
django_statsd/templates.py
django_statsd/urls.py
django_statsd/utils.py
django_statsd-2.7.0.dist-info/METADATA
django_statsd-2.7.0.dist-info/WHEEL
django_statsd-2.7.0.dist-info/top_level.txt
django_statsd-2.7.0.dist-info/RECORD
