Metadata-Version: 2.1
Name: django-statsd
Version: 2.7.0
Summary: django-statsd is a Django app that submits query and view durations to Etsy's statsd.
Home-page: https://github.com/WoLpH/django-statsd
Author: Rick van Hattem
Author-email: Rick.van.Hattem@Fawo.nl
License: BSD
Classifier: Development Status :: 5 - Production/Stable
Classifier: Environment :: Web Environment
Classifier: Framework :: Django
Classifier: Framework :: Django :: 2.2
Classifier: Framework :: Django :: 3.0
Classifier: Intended Audience :: Developers
Classifier: License :: OSI Approved :: BSD License
Classifier: Operating System :: OS Independent
Classifier: Programming Language :: Python
Classifier: Programming Language :: Python :: 2
Classifier: Programming Language :: Python :: 2.7
Classifier: Programming Language :: Python :: 3
Classifier: Programming Language :: Python :: 3.5
Classifier: Programming Language :: Python :: 3.6
Classifier: Programming Language :: Python :: 3.7
Classifier: Programming Language :: Python :: 3.8
Classifier: Programming Language :: Python :: 3 :: Only
Classifier: Topic :: Internet :: WWW/HTTP
Requires-Dist: python-statsd >=1.7.2
Provides-Extra: docs
Requires-Dist: django >=1.11 ; extra == 'docs'
Requires-Dist: mock ; extra == 'docs'
Requires-Dist: sphinx >=1.7.2 ; extra == 'docs'
Provides-Extra: tests
Requires-Dist: mock ; extra == 'tests'
Requires-Dist: pytest ; extra == 'tests'
Requires-Dist: pytest-cache ; extra == 'tests'
Requires-Dist: pytest-cov ; extra == 'tests'
Requires-Dist: pytest-django ; extra == 'tests'
Requires-Dist: pytest-flakes ; extra == 'tests'
Requires-Dist: pytest-pep8 ; extra == 'tests'
